chippyash/__init__.py
chippyash/chippyash.py
chippyash-0.0.2.dist-info/LICENSE
chippyash-0.0.2.dist-info/METADATA
chippyash-0.0.2.dist-info/WHEEL
chippyash-0.0.2.dist-info/top_level.txt
chippyash-0.0.2.dist-info/RECORD
