Metadata-Version: 2.1
Name: chippyash
Version: 0.0.2
Summary: chippy
Home-page: https://github.com/1912193931/awesome-godot
Author: hurpe
Author-email: hurpe.ma@gmail.com
License: MIT
Platform: UNKNOWN
